{
  "project_info": {
    "project_number": "664369494935",
    "project_id": "healthathand-1a1f8",
    "storage_bucket": "healthathand-1a1f8.appspot.com"
  },
  "client": [
    {
      "client_info": {
        "mobilesdk_app_id": "1:664369494935:android:ba39bc7e00c716cc3c62d2",
        "android_client_info": {
          "package_name": "com.sp.healthathand"
        }
      },
      "oauth_client": [
        {
          "client_id": "664369494935-h42fjnjaqugg2vkekoo9895har18uovd.apps.googleusercontent.com",
          "client_type": 3
        }
      ],
      "api_key": [
        {
          "current_key": "AIzaSyCCWG7i9rP5A_uvVhGot11nMV1KVoeX8jE"
        }
      ],
      "services": {
        "appinvite_service": {
          "other_platform_oauth_client": [
            {
              "client_id": "664369494935-h42fjnjaqugg2vkekoo9895har18uovd.apps.googleusercontent.com",
              "client_type": 3
            }
          ]
        }
      }
    }
  ],
  "configuration_version": "1"
}